ghat/__init__.py
ghat/template.py
github_action_templates-0.0.5.dist-info/LICENSE
github_action_templates-0.0.5.dist-info/METADATA
github_action_templates-0.0.5.dist-info/WHEEL
github_action_templates-0.0.5.dist-info/top_level.txt
github_action_templates-0.0.5.dist-info/RECORD
