Metadata-Version: 2.1
Name: github-action-templates
Version: 0.0.5
Summary: Template GitHub Actions
Home-page: https://github.com/chatton/github-action-templates
Author: Cian Hatton
Author-email: cianhatton@gmail.com
License: UNKNOWN
Platform: UNKNOWN
License-File: LICENSE
